pyAMaFiL/mag_field_lin_fff.py
pyAMaFiL/mag_field_proc.py
pyAMaFiL/WWNLFFFReconstruction.cpython-310-x86_64-linux-gnu.so
pyAMaFiL/mag_field_wrapper.py
pyAMaFiL/__init__.py
pyamafil-1.1.3.dist-info/WHEEL
pyamafil-1.1.3.dist-info/top_level.txt
pyamafil-1.1.3.dist-info/RECORD
pyamafil-1.1.3.dist-info/METADATA
pyamafil-1.1.3.dist-info/licenses/LICENCE.md
