Metadata-Version: 2.4
Name: pyAMaFiL
Version: 1.1.3
Summary: Library for reconstructing solar magnetic fields with NLFFF optimization approach
Author-email: "Alexey G. Stupishin" <agstup@yandex.ru>
Maintainer-email: "Alexey G. Stupishin" <agstup@yandex.ru>
Project-URL: Issues, https://github.com/Alexey-Stupishin/pyAMaFiL/issues
Project-URL: Repository, https://github.com/Alexey-Stupishin/pyAMaFiL
Keywords: Sun,magnetic fields,NLFFF,solar physics
Classifier: Development Status :: 3 - Alpha
Classifier: Intended Audience :: Science/Research
Classifier: Programming Language :: Python :: 3
Classifier: Programming Language :: Python :: 3.10
Classifier: Programming Language :: Python :: 3.11
Classifier: Programming Language :: Python :: 3.12
License-File: LICENCE.md
Requires-Dist: numpy
Requires-Dist: scipy
Requires-Dist: sunpy
Requires-Dist: importlib-metadata; python_version >= "3.10"
Dynamic: license-file
